LICENSE
MANIFEST.in
README.md
setup.py
dataplus/__init__.py
dataplus/__version__.py
dataplus/datasync.py
dataplus.egg-info/PKG-INFO
dataplus.egg-info/SOURCES.txt
dataplus.egg-info/dependency_links.txt
dataplus.egg-info/requires.txt
dataplus.egg-info/top_level.txt