Metadata-Version: 2.1
Name: dataplus
Version: 0.1.3
Summary: A tool written in Python to synchronize databases in a simple way
Home-page: https://github.com/hupong/datasync
Author: Paul Hu
Author-email: hupong@gmail.com
License: MIT
Platform: UNKNOWN
Classifier: License :: OSI Approved :: MIT License
Classifier: Programming Language :: Python
Classifier: Programming Language :: Python :: 3
Classifier: Programming Language :: Python :: 3.6
Classifier: Programming Language :: Python :: Implementation :: CPython
Classifier: Programming Language :: Python :: Implementation :: PyPy
Requires-Python: >=3.6.0
Provides-Extra: fancy feature
